yaqd_microchip/VERSION
yaqd_microchip/__init__.py
yaqd_microchip/__version__.py
yaqd_microchip/_mcp3428.py
yaqd_microchip/_mcp9600.py
yaqd_microchip/mcp3428.avpr
yaqd_microchip/mcp3428.toml
yaqd_microchip/mcp9600.avpr
yaqd_microchip/mcp9600.toml
yaqd_microchip-2021.3.0.dist-info/entry_points.txt
yaqd_microchip-2021.3.0.dist-info/LICENSE
yaqd_microchip-2021.3.0.dist-info/WHEEL
yaqd_microchip-2021.3.0.dist-info/METADATA
yaqd_microchip-2021.3.0.dist-info/RECORD
